MANIFEST.in
build_wrapper.py
setup.py
aduana/__init__.py
aduana/frontera.py
aduana.egg-info/PKG-INFO
aduana.egg-info/SOURCES.txt
aduana.egg-info/dependency_links.txt
aduana.egg-info/pbr.json
aduana.egg-info/requires.txt
aduana.egg-info/top_level.txt
aduana/bin/aduana-server-cert.py
aduana/bin/aduana-server.py
lib/lib/mman.h
lib/lib/smaz.c
lib/lib/smaz.h
lib/lib/xxhash.c
lib/lib/xxhash.h
lib/lib/lmdb/lmdb.h
lib/lib/lmdb/mdb.c
lib/lib/lmdb/midl.c
lib/lib/lmdb/midl.h
lib/src/bf_scheduler.c
lib/src/bf_scheduler.h
lib/src/domain_temp.c
lib/src/domain_temp.h
lib/src/hits.c
lib/src/hits.h
lib/src/hits_scorer.c
lib/src/hits_scorer.h
lib/src/link_stream.h
lib/src/mmap_array.c
lib/src/mmap_array.h
lib/src/page_db.c
lib/src/page_db.h
lib/src/page_rank.c
lib/src/page_rank.h
lib/src/page_rank_scorer.c
lib/src/page_rank_scorer.h
lib/src/scheduler.c
lib/src/scheduler.h
lib/src/scorer.h
lib/src/txn_manager.c
lib/src/txn_manager.h
lib/src/util.c
lib/src/util.h
lib/test/CuTest.h