Metadata-Version: 1.1
Name: aduana
Version: 0.2.1
Summary: Bindings for Aduana library
Home-page: https://github.com/scrapinghub/aduana
Author: Pedro Lopez-Adeva Fernandez-Layos
Author-email: pedro@scrapinghub.com
License: UNKNOWN
Keywords: crawler,frontier,scrapy,web,requests
Platform: UNKNOWN
Classifier: Development Status :: 4 - Beta
Classifier: Environment :: Console
Classifier: Intended Audience :: Developers
Classifier: License :: OSI Approved :: BSD License
Classifier: Operating System :: POSIX
Classifier: Programming Language :: Python
Classifier: Programming Language :: Python :: 2
Classifier: Programming Language :: Python :: 2.7
Classifier: Topic :: Internet :: WWW/HTTP
Classifier: Topic :: Software Development :: Libraries :: Application Frameworks
Classifier: Topic :: Software Development :: Libraries :: Python Modules
